LICENSE
README.md
setup.py
demeter_fetch/__init__.py
demeter_fetch/main.py
demeter_fetch.egg-info/PKG-INFO
demeter_fetch.egg-info/SOURCES.txt
demeter_fetch.egg-info/dependency_links.txt
demeter_fetch.egg-info/entry_points.txt
demeter_fetch.egg-info/requires.txt
demeter_fetch.egg-info/top_level.txt
demeter_fetch/common/__init__.py
demeter_fetch/common/_typing.py
demeter_fetch/common/nodes.py
demeter_fetch/common/utils.py
demeter_fetch/core/__init__.py
demeter_fetch/core/commands.py
demeter_fetch/core/config.py
demeter_fetch/core/downloader.py
demeter_fetch/core/engine.py
demeter_fetch/processor_aave/__init__.py
demeter_fetch/processor_aave/aave_utils.py
demeter_fetch/processor_aave/minute.py
demeter_fetch/processor_aave/tick.py
demeter_fetch/processor_gmx2/__init__.py
demeter_fetch/processor_gmx2/gmx2_utils.py
demeter_fetch/processor_gmx2/minute.py
demeter_fetch/processor_gmx2/pool.py
demeter_fetch/processor_gmx2/pool_value_util.py
demeter_fetch/processor_gmx2/price.py
demeter_fetch/processor_gmx2/tick.py
demeter_fetch/processor_squeeth/__init__.py
demeter_fetch/processor_squeeth/minute.py
demeter_fetch/processor_uniswap/__init__.py
demeter_fetch/processor_uniswap/minute.py
demeter_fetch/processor_uniswap/position.py
demeter_fetch/processor_uniswap/relative_price.py
demeter_fetch/processor_uniswap/tick.py
demeter_fetch/processor_uniswap/uniswap_utils.py
demeter_fetch/sources/__init__.py
demeter_fetch/sources/big_query.py
demeter_fetch/sources/big_query_utils.py
demeter_fetch/sources/chifra.py
demeter_fetch/sources/chifra_utils.py
demeter_fetch/sources/rpc.py
demeter_fetch/sources/rpc_utils.py
demeter_fetch/sources/source_core.py
demeter_fetch/sources/source_utils.py
demeter_fetch/tools/__init__.py
demeter_fetch/tools/aave.py
demeter_fetch/tools/abi.py
demeter_fetch/tools/bigquery_tools.py
demeter_fetch/tools/gmx_config.py
demeter_fetch/tools/time_tools.py
demeter_fetch/tools/gmx/__init__.py
demeter_fetch/tools/gmx/keys.py
tests/test_aave_full.py
tests/test_aave_full_big_query.py
tests/test_aave_full_rpc.py
tests/test_core.py
tests/test_gmx_v2_pool.py
tests/test_rpc.py
tests/test_squeeth_full.py
tests/test_squeeth_full_rpc.py
tests/test_uni_full.py
tests/test_uni_full_big_query.py
