Metadata-Version: 2.2
Name: demeter-fetch
Version: 1.3.10
Summary: demeter fetch tool
Home-page: 
Author: zelos research
Author-email: zelos@antalpha.com
License: MIT
Requires-Python: >=3.11
License-File: LICENSE
Requires-Dist: numpy>=1.26.3
Requires-Dist: pandas>=2.2.1
Requires-Dist: protobuf>=4.25.2
Requires-Dist: Requests>=2.31.0
Requires-Dist: toml>=0.10.2
Requires-Dist: tqdm>=4.66.2
Requires-Dist: google-cloud-bigquery>=3.19.0
Requires-Dist: db-dtypes>=1.2.0
Requires-Dist: argparse>=1.4.0
Requires-Dist: sqlitedict>=2.1.0
Requires-Dist: eth_abi>=5.2.0
Dynamic: author
Dynamic: author-email
Dynamic: license
Dynamic: requires-dist
Dynamic: requires-python
Dynamic: summary
